baco.py
pybaco.py
setup.py
pybaco.egg-info/PKG-INFO
pybaco.egg-info/SOURCES.txt
pybaco.egg-info/dependency_links.txt
pybaco.egg-info/top_level.txt