Metadata-Version: 1.0
Name: pybaco
Version: 0.3.0
Summary: Python Base Converter
Home-page: http://github.com/rougeh/pybaco
Author: Marco Rougeth
Author-email: marco@rougeth.com
License: UNKNOWN
Platform: UNKNOWN
